{
  "description": "A high-security digital forensics lab with specialized equipment for analyzing encrypted network traffic and tracking suspicious devices.",
  "rooms": [
    {
      "id": "main_forensic_workbench",
      "name": "Main Forensic Workbench",
      "properties": {
        "type": "workstation"
      },
      "connected_to_room_ids": [
        "secure_storage_vault",
        "network_operations_corner",
        "break_area",
        "evidence_lockers"
      ]
    },
    {
      "id": "secure_storage_vault",
      "name": "Secure Storage Vault",
      "properties": {
        "type": "storage"
      },
      "connected_to_room_ids": [
        "main_forensic_workbench"
      ]
    },
    {
      "id": "network_operations_corner",
      "name": "Network Operations Corner",
      "properties": {
        "type": "server_room"
      },
      "connected_to_room_ids": [
        "main_forensic_workbench"
      ]
    },
    {
      "id": "break_area",
      "name": "Break Area",
      "properties": {
        "type": "casual"
      },
      "connected_to_room_ids": [
        "main_forensic_workbench"
      ]
    },
    {
      "id": "evidence_lockers",
      "name": "Evidence Lockers",
      "properties": {
        "type": "storage"
      },
      "connected_to_room_ids": [
        "main_forensic_workbench"
      ]
    }
  ],
  "objects": [
    {
      "id": "forensic_workstation_cluster_1",
      "name": "Forensic Workstation Cluster",
      "type": "FURNITURE",
      "location_id": "in:main_forensic_workbench",
      "properties": {
        "size": [
          2.0,
          1.5,
          0.8
        ],
        "weight": 75.0,
        "is_container": true,
        "brand": "Dell",
        "model_number": "Precision 7865"
      },
      "states": {
        "is_on": false
      }
    },
    {
      "id": "anti_static_mat_1",
      "name": "Anti-Static Mat",
      "type": "ITEM",
      "location_id": "on:forensic_workstation_cluster_1",
      "properties": {
        "weight": 1.5,
        "color": "black",
        "material": "rubber"
      },
      "states": {}
    },
    {
      "id": "tool_mounting_board_1",
      "name": "Tool Mounting Board",
      "type": "FURNITURE",
      "location_id": "in:main_forensic_workbench",
      "properties": {
        "size": [
          1.2,
          0.6,
          0.05
        ],
        "weight": 5.0,
        "is_container": true,
        "material": "pegboard"
      },
      "states": {}
    },
    {
      "id": "encrypted_hard_drive_1",
      "name": "Encrypted Hard Drive",
      "type": "ITEM",
      "location_id": "on:forensic_workstation_cluster_1",
      "properties": {
        "weight": 0.1,
        "color": "silver",
        "material": "metal",
        "capacity": "1TB",
        "is_container": false
      },
      "states": {
        "is_uploaded": false
      }
    },
    {
      "id": "rfid_scanner_1",
      "name": "RFID Scanner",
      "type": "ITEM",
      "location_id": "on:forensic_workstation_cluster_1",
      "properties": {
        "weight": 0.5,
        "color": "black",
        "brand": "Zebra",
        "model_number": "FX9600"
      },
      "states": {
        "is_charged": false
      }
    },
    {
      "id": "soldering_station_1",
      "name": "Soldering Station",
      "type": "FURNITURE",
      "location_id": "in:main_forensic_workbench",
      "properties": {
        "size": [
          0.4,
          0.3,
          0.2
        ],
        "weight": 3.0,
        "brand": "Weller",
        "model_number": "WLC100",
        "is_container": true
      },
      "states": {
        "is_on": false
      }
    },
    {
      "id": "label_maker_1",
      "name": "Label Maker",
      "type": "ITEM",
      "location_id": "on:forensic_workstation_cluster_1",
      "properties": {
        "weight": 0.8,
        "color": "white",
        "brand": "Brother",
        "model_number": "PT-D210"
      },
      "states": {
        "is_charged": false
      }
    },
    {
      "id": "usb_hub_1",
      "name": "USB Hub",
      "type": "ITEM",
      "location_id": "on:forensic_workstation_cluster_1",
      "properties": {
        "weight": 0.3,
        "color": "black",
        "ports": 10,
        "brand": "Anker"
      },
      "states": {}
    },
    {
      "id": "magnifying_lamp_1",
      "name": "Magnifying Lamp",
      "type": "FURNITURE",
      "location_id": "in:main_forensic_workbench",
      "properties": {
        "size": [
          0.5,
          0.5,
          0.8
        ],
        "weight": 2.5,
        "brand": "Brightech"
      },
      "states": {
        "is_on": false
      }
    },
    {
      "id": "poster_1",
      "name": "WPA3 Decryption Flowchart Poster",
      "type": "ITEM",
      "location_id": "in:main_forensic_workbench",
      "properties": {
        "weight": 0.2,
        "color": "multicolor",
        "material": "paper"
      },
      "states": {}
    },
    {
      "id": "sticky_notes_1",
      "name": "Sticky Notes",
      "type": "ITEM",
      "location_id": "on:forensic_workstation_cluster_1",
      "properties": {
        "weight": 0.05,
        "color": "yellow",
        "material": "paper"
      },
      "states": {}
    },
    {
      "id": "energy_drink_can_1",
      "name": "Empty Energy Drink Can",
      "type": "ITEM",
      "location_id": "on:forensic_workstation_cluster_1",
      "properties": {
        "weight": 0.1,
        "color": "silver",
        "brand": "Crunch Berry"
      },
      "states": {}
    },
    {
      "id": "biometric_safe_1",
      "name": "Biometric Safe",
      "type": "FURNITURE",
      "location_id": "in:secure_storage_vault",
      "properties": {
        "size": [
          0.5,
          0.4,
          1.2
        ],
        "weight": 85.0,
        "is_container": true,
        "brand": "SentrySafe"
      },
      "states": {
        "is_locked": false,
        "is_open": false
      }
    },
    {
      "id": "heavy_duty_shelving_1",
      "name": "Heavy-Duty Shelving",
      "type": "FURNITURE",
      "location_id": "in:secure_storage_vault",
      "properties": {
        "size": [
          2.0,
          0.6,
          2.0
        ],
        "weight": 90.0,
        "is_container": true,
        "material": "steel"
      },
      "states": {}
    },
    {
      "id": "seized_smartphone_1",
      "name": "Seized Smartphone",
      "type": "ITEM",
      "location_id": "in:biometric_safe_1",
      "properties": {
        "weight": 0.2,
        "color": "black",
        "brand": "Apple",
        "model": "iPhone 14"
      },
      "states": {
        "is_charged": false
      }
    },
    {
      "id": "access_logbook_1",
      "name": "Access Logbook",
      "type": "ITEM",
      "location_id": "on:heavy_duty_shelving_1",
      "properties": {
        "weight": 0.5,
        "color": "black",
        "material": "paper"
      },
      "states": {
        "is_signed": false
      }
    },
    {
      "id": "fire_extinguisher_1",
      "name": "Fire Extinguisher",
      "type": "ITEM",
      "location_id": "in:secure_storage_vault",
      "properties": {
        "weight": 5.0,
        "color": "red",
        "brand": "Kidde"
      },
      "states": {}
    },
    {
      "id": "glove_dispenser_1",
      "name": "Glove Dispenser",
      "type": "ITEM",
      "location_id": "on:heavy_duty_shelving_1",
      "properties": {
        "weight": 1.0,
        "color": "white",
        "material": "plastic"
      },
      "states": {}
    },
    {
      "id": "trophy_1",
      "name": "Dusty Trophy",
      "type": "ITEM",
      "location_id": "in:secure_storage_vault",
      "properties": {
        "weight": 1.5,
        "color": "gold",
        "material": "metal"
      },
      "states": {}
    },
    {
      "id": "osha_poster_1",
      "name": "Faded OSHA Poster",
      "type": "ITEM",
      "location_id": "in:secure_storage_vault",
      "properties": {
        "weight": 0.1,
        "color": "multicolor",
        "material": "paper"
      },
      "states": {}
    },
    {
      "id": "server_rack_1",
      "name": "19\" Server Rack",
      "type": "FURNITURE",
      "location_id": "in:network_operations_corner",
      "properties": {
        "size": [
          0.6,
          1.0,
          2.0
        ],
        "weight": 95.0,
        "is_container": true,
        "brand": "APC"
      },
      "states": {
        "is_open": false
      }
    },
    {
      "id": "whiteboard_1",
      "name": "Wall-Mounted Whiteboard",
      "type": "FURNITURE",
      "location_id": "in:network_operations_corner",
      "properties": {
        "size": [
          1.5,
          1.0,
          0.05
        ],
        "weight": 15.0,
        "material": "melamine"
      },
      "states": {}
    },
    {
      "id": "sdr_dongle_1",
      "name": "SDR Dongle",
      "type": "ITEM",
      "location_id": "on:server_rack_1",
      "properties": {
        "weight": 0.1,
        "color": "black",
        "brand": "HackRF",
        "model": "One"
      },
      "states": {
        "is_charged": false
      }
    },
    {
      "id": "gps_spoofer_1",
      "name": "GPS Spoofer",
      "type": "ITEM",
      "location_id": "in:server_rack_1",
      "properties": {
        "weight": 0.5,
        "color": "black",
        "brand": "GPS-SYN"
      },
      "states": {
        "is_locked": false
      }
    },
    {
      "id": "kvm_switch_1",
      "name": "KVM Switch",
      "type": "ITEM",
      "location_id": "on:server_rack_1",
      "properties": {
        "weight": 0.3,
        "color": "black",
        "ports": 4,
        "brand": "Tripp Lite"
      },
      "states": {}
    },
    {
      "id": "patch_panel_1",
      "name": "Patch Panel",
      "type": "ITEM",
      "location_id": "on:server_rack_1",
      "properties": {
        "weight": 1.0,
        "color": "black",
        "ports": 24,
        "brand": "Cable Matters"
      },
      "states": {}
    },
    {
      "id": "coffee_mug_1",
      "name": "Coffee Mug",
      "type": "ITEM",
      "location_id": "on:server_rack_1",
      "properties": {
        "weight": 0.4,
        "color": "white",
        "material": "ceramic"
      },
      "states": {}
    },
    {
      "id": "ieee_journals_1",
      "name": "Stack of IEEE Journals",
      "type": "ITEM",
      "location_id": "in:network_operations_corner",
      "properties": {
        "weight": 3.0,
        "color": "multicolor",
        "material": "paper"
      },
      "states": {}
    },
    {
      "id": "pelican_case_1",
      "name": "Pelican Case",
      "type": "FURNITURE",
      "location_id": "on:heavy_duty_shelving_1",
      "properties": {
        "size": [
          0.6,
          0.4,
          0.3
        ],
        "weight": 60.0,
        "is_container": true,
        "brand": "Pelican"
      },
      "states": {
        "is_locked": false
      }
    },
    {
      "id": "keycard_1",
      "name": "Keycard",
      "type": "ITEM",
      "location_id": "in:break_area",
      "properties": {
        "weight": 0.05,
        "color": "white",
        "material": "plastic",
        "provides_abilities": [
          "lock"
        ]
      },
      "states": {}
    },
    {
      "id": "charger_1",
      "name": "USB Charger",
      "type": "ITEM",
      "location_id": "in:break_area",
      "properties": {
        "weight": 0.1,
        "color": "white",
        "brand": "Anker",
        "provides_abilities": [
          "recharge"
        ]
      },
      "states": {}
    },
    {
      "id": "pen_1",
      "name": "Pen",
      "type": "ITEM",
      "location_id": "in:break_area",
      "properties": {
        "weight": 0.02,
        "color": "black",
        "brand": "Pilot",
        "provides_abilities": [
          "sign",
          "scratch"
        ]
      },
      "states": {}
    },
    {
      "id": "network_cable_1",
      "name": "Cat6 Cable",
      "type": "ITEM",
      "location_id": "on:server_rack_1",
      "properties": {
        "weight": 0.2,
        "color": "blue",
        "length": "2m"
      },
      "states": {}
    },
    {
      "id": "evidence_locker_1",
      "name": "Evidence Locker",
      "type": "FURNITURE",
      "location_id": "in:evidence_lockers",
      "properties": {
        "size": [
          0.5,
          0.5,
          1.0
        ],
        "weight": 70.0,
        "is_container": true
      },
      "states": {
        "is_locked": false,
        "is_open": false
      }
    },
    {
      "id": "usb_drive_1",
      "name": "USB Drive",
      "type": "ITEM",
      "location_id": "in:evidence_locker_1",
      "properties": {
        "weight": 0.02,
        "color": "black",
        "capacity": "32GB"
      },
      "states": {
        "is_scratched": false
      }
    },
    {
      "id": "usb_drive_2",
      "name": "USB Drive",
      "type": "ITEM",
      "location_id": "in:evidence_locker_1",
      "properties": {
        "weight": 0.02,
        "color": "black",
        "capacity": "32GB"
      },
      "states": {
        "is_scratched": false
      }
    },
    {
      "id": "usb_drive_3",
      "name": "USB Drive",
      "type": "ITEM",
      "location_id": "in:evidence_locker_1",
      "properties": {
        "weight": 0.02,
        "color": "black",
        "capacity": "32GB"
      },
      "states": {
        "is_scratched": false
      }
    },
    {
      "id": "usb_drive_4",
      "name": "USB Drive",
      "type": "ITEM",
      "location_id": "in:evidence_locker_1",
      "properties": {
        "weight": 0.02,
        "color": "black",
        "capacity": "32GB"
      },
      "states": {
        "is_scratched": false
      }
    },
    {
      "id": "usb_drive_5",
      "name": "USB Drive",
      "type": "ITEM",
      "location_id": "in:evidence_locker_1",
      "properties": {
        "weight": 0.04,
        "color": "black",
        "capacity": "32GB"
      },
      "states": {
        "is_scratched": true
      }
    },
    {
      "id": "jacket_1",
      "name": "Jacket",
      "type": "ITEM",
      "location_id": "in:break_area",
      "properties": {
        "weight": 1.0,
        "color": "black",
        "material": "polyester",
        "is_container": true
      },
      "states": {
        "is_open": false
      }
    },
    {
      "id": "keycard_2",
      "name": "Keycard",
      "type": "ITEM",
      "location_id": "in:jacket_1",
      "properties": {
        "weight": 0.05,
        "color": "white",
        "material": "plastic",
        "provides_abilities": [
          "lock"
        ]
      },
      "states": {}
    },
    {
      "id": "router_1",
      "name": "Disassembled Router",
      "type": "ITEM",
      "location_id": "on:soldering_station_1",
      "properties": {
        "weight": 0.5,
        "color": "black",
        "brand": "Cisco"
      },
      "states": {
        "is_broken": false
      }
    },
    {
      "id": "screwdriver_1",
      "name": "Screwdriver",
      "type": "ITEM",
      "location_id": "on:tool_mounting_board_1",
      "properties": {
        "weight": 0.2,
        "color": "red",
        "brand": "Klein Tools",
        "provides_abilities": [
          "damage"
        ]
      },
      "states": {}
    },
    {
      "id": "hammer_1",
      "name": "Hammer",
      "type": "ITEM",
      "location_id": "on:tool_mounting_board_1",
      "properties": {
        "weight": 0.5,
        "color": "black",
        "brand": "Estwing",
        "provides_abilities": [
          "damage"
        ]
      },
      "states": {}
    }
  ],
  "abilities": [
    "damage",
    "lock",
    "open",
    "recharge",
    "scratch",
    "sign",
    "turn_on",
    "close"
  ]
}