{
  "description": "A labyrinthine Legal Archive & Processing Center with overflowing document shelves, a high-security vault, and a document restoration lab, all under the pressure of looming legal deadlines.",
  "rooms": [
    {
      "id": "main_processing_hub",
      "name": "Main Processing Hub",
      "properties": {
        "type": "office"
      },
      "connected_to_room_ids": [
        "high_security_vault",
        "document_restoration_lab",
        "storage_catacombs"
      ]
    },
    {
      "id": "high_security_vault",
      "name": "High-Security Vault",
      "properties": {
        "type": "secure_storage"
      },
      "connected_to_room_ids": [
        "main_processing_hub"
      ]
    },
    {
      "id": "document_restoration_lab",
      "name": "Document Restoration Lab",
      "properties": {
        "type": "workshop"
      },
      "connected_to_room_ids": [
        "main_processing_hub",
        "storage_catacombs"
      ]
    },
    {
      "id": "storage_catacombs",
      "name": "Storage Catacombs",
      "properties": {
        "type": "archive"
      },
      "connected_to_room_ids": [
        "main_processing_hub",
        "document_restoration_lab"
      ]
    }
  ],
  "objects": [
    {
      "id": "u_shaped_workstation_1",
      "name": "U-Shaped Workstation",
      "type": "FURNITURE",
      "location_id": "in:main_processing_hub",
      "properties": {
        "size": [
          3.0,
          2.5,
          0.8
        ],
        "weight": 75.0,
        "is_container": true,
        "material": "particle_board",
        "color": "beige"
      },
      "states": {
        "is_open": false
      }
    },
    {
      "id": "ergonomic_chair_1",
      "name": "Ergonomic Office Chair",
      "type": "FURNITURE",
      "location_id": "on:u_shaped_workstation_1",
      "properties": {
        "size": [
          0.6,
          0.6,
          1.0
        ],
        "weight": 12.0,
        "is_container": false,
        "material": "mesh",
        "color": "black",
        "brand": "Herman Miller"
      },
      "states": {
        "is_broken": true
      }
    },
    {
      "id": "ergonomic_chair_2",
      "name": "Ergonomic Office Chair",
      "type": "FURNITURE",
      "location_id": "on:u_shaped_workstation_1",
      "properties": {
        "size": [
          0.6,
          0.6,
          1.0
        ],
        "weight": 12.0,
        "is_container": false,
        "material": "mesh",
        "color": "black",
        "brand": "Herman Miller"
      },
      "states": {}
    },
    {
      "id": "ergonomic_chair_3",
      "name": "Ergonomic Office Chair",
      "type": "FURNITURE",
      "location_id": "on:u_shaped_workstation_1",
      "properties": {
        "size": [
          0.6,
          0.6,
          1.0
        ],
        "weight": 12.0,
        "is_container": false,
        "material": "mesh",
        "color": "black",
        "brand": "Herman Miller"
      },
      "states": {}
    },
    {
      "id": "industrial_printer_1",
      "name": "Industrial Printer",
      "type": "FURNITURE",
      "location_id": "in:main_processing_hub",
      "properties": {
        "size": [
          1.2,
          0.8,
          1.5
        ],
        "weight": 60.0,
        "is_container": false,
        "material": "steel",
        "color": "gray",
        "brand": "Xerox",
        "model_number": "Phaser 8860"
      },
      "states": {
        "is_dirty": true
      }
    },
    {
      "id": "digital_clock_1",
      "name": "Wall-Mounted Digital Clock",
      "type": "FURNITURE",
      "location_id": "in:main_processing_hub",
      "properties": {
        "size": [
          0.3,
          0.1,
          0.3
        ],
        "weight": 1.5,
        "is_container": false,
        "material": "plastic",
        "color": "black",
        "brand": "Sharp"
      },
      "states": {
        "is_dirty": true
      }
    },
    {
      "id": "bulletin_board_1",
      "name": "Bulletin Board",
      "type": "FURNITURE",
      "location_id": "in:main_processing_hub",
      "properties": {
        "size": [
          1.5,
          0.1,
          1.0
        ],
        "weight": 8.0,
        "is_container": true,
        "material": "cork",
        "color": "brown"
      },
      "states": {}
    },
    {
      "id": "priority_inbox_1",
      "name": "Priority Inbox",
      "type": "FURNITURE",
      "location_id": "on:u_shaped_workstation_1",
      "properties": {
        "size": [
          0.4,
          0.3,
          0.2
        ],
        "weight": 3.0,
        "is_container": true,
        "material": "plastic",
        "color": "red"
      },
      "states": {
        "is_open": false
      }
    },
    {
      "id": "stamp_of_authenticity_1",
      "name": "Stamp of Authenticity",
      "type": "ITEM",
      "location_id": "in:main_processing_hub",
      "properties": {
        "weight": 0.2,
        "color": "black",
        "material": "wood",
        "brand": "Trodat",
        "provides_abilities": [
          "glue"
        ]
      },
      "states": {}
    },
    {
      "id": "case_tracker_terminal_1",
      "name": "Case Tracker Terminal",
      "type": "FURNITURE",
      "location_id": "on:u_shaped_workstation_1",
      "properties": {
        "size": [
          0.5,
          0.4,
          0.5
        ],
        "weight": 15.0,
        "is_container": false,
        "material": "plastic",
        "color": "beige",
        "brand": "Dell"
      },
      "states": {
        "is_formatted": false
      }
    },
    {
      "id": "security_token_1",
      "name": "Security Token",
      "type": "ITEM",
      "location_id": "in:u_shaped_workstation_1",
      "properties": {
        "weight": 0.1,
        "color": "blue",
        "material": "plastic",
        "brand": "RSA",
        "provides_abilities": [
          "format"
        ]
      },
      "states": {}
    },
    {
      "id": "coffee_maker_1",
      "name": "Coffee Maker",
      "type": "FURNITURE",
      "location_id": "in:main_processing_hub",
      "properties": {
        "size": [
          0.3,
          0.2,
          0.4
        ],
        "weight": 5.0,
        "is_container": true,
        "material": "plastic",
        "color": "black",
        "brand": "Keurig"
      },
      "states": {
        "is_dirty": true
      }
    },
    {
      "id": "legal_forms_stack_1",
      "name": "Stack of Blank Legal Forms",
      "type": "ITEM",
      "location_id": "on:u_shaped_workstation_1",
      "properties": {
        "weight": 2.0,
        "color": "white",
        "material": "paper",
        "quantity": 50
      },
      "states": {}
    },
    {
      "id": "wheeled_cart_1",
      "name": "Wheeled Cart",
      "type": "FURNITURE",
      "location_id": "in:main_processing_hub",
      "properties": {
        "size": [
          1.0,
          0.6,
          0.9
        ],
        "weight": 25.0,
        "is_container": true,
        "material": "metal",
        "color": "gray"
      },
      "states": {
        "is_broken": true
      }
    },
    {
      "id": "judge_portrait_1",
      "name": "Framed Portrait of a Judge",
      "type": "FURNITURE",
      "location_id": "in:main_processing_hub",
      "properties": {
        "size": [
          0.6,
          0.1,
          0.8
        ],
        "weight": 3.0,
        "is_container": false,
        "material": "wood",
        "color": "brown"
      },
      "states": {
        "is_dirty": true
      }
    },
    {
      "id": "dead_fern_1",
      "name": "Dead Potted Fern",
      "type": "FURNITURE",
      "location_id": "in:main_processing_hub",
      "properties": {
        "size": [
          0.4,
          0.4,
          0.8
        ],
        "weight": 5.0,
        "is_container": true,
        "material": "ceramic",
        "color": "green"
      },
      "states": {
        "is_harvested": false
      }
    },
    {
      "id": "donut_box_1",
      "name": "Half-Empty Box of Donuts",
      "type": "ITEM",
      "location_id": "on:u_shaped_workstation_1",
      "properties": {
        "weight": 0.5,
        "color": "pink",
        "material": "cardboard",
        "brand": "Dunkin'"
      },
      "states": {}
    },
    {
      "id": "steel_door_1",
      "name": "Reinforced Steel Door",
      "type": "FURNITURE",
      "location_id": "in:high_security_vault",
      "properties": {
        "size": [
          2.1,
          0.1,
          2.4
        ],
        "weight": 250.0,
        "is_container": false,
        "material": "steel",
        "color": "gray"
      },
      "states": {
        "is_open": false
      }
    },
    {
      "id": "overhead_light_1",
      "name": "Motion-Sensitive Overhead Light",
      "type": "FURNITURE",
      "location_id": "in:high_security_vault",
      "properties": {
        "size": [
          0.3,
          0.3,
          0.1
        ],
        "weight": 2.0,
        "is_container": false,
        "material": "plastic",
        "color": "white",
        "brand": "Philips"
      },
      "states": {
        "is_broken": true
      }
    },
    {
      "id": "habeas_file_4472_1",
      "name": "Sealed Habeas Corpus File #4472",
      "type": "ITEM",
      "location_id": "in:high_security_vault",
      "properties": {
        "weight": 1.5,
        "color": "manila",
        "material": "paper",
        "confidentiality": "top_secret"
      },
      "states": {
        "is_hidden": false
      }
    },
    {
      "id": "biometric_scanner_1",
      "name": "Biometric Scanner",
      "type": "FURNITURE",
      "location_id": "in:high_security_vault",
      "properties": {
        "size": [
          0.2,
          0.2,
          0.3
        ],
        "weight": 3.0,
        "is_container": false,
        "material": "plastic",
        "color": "black",
        "brand": "HID Global"
      },
      "states": {
        "is_broken": true
      }
    },
    {
      "id": "fireproof_safe_1",
      "name": "Fireproof Safe",
      "type": "FURNITURE",
      "location_id": "in:high_security_vault",
      "properties": {
        "size": [
          0.6,
          0.5,
          0.5
        ],
        "weight": 60.0,
        "is_container": true,
        "material": "steel",
        "color": "black",
        "brand": "SentrySafe"
      },
      "states": {
        "is_open": false
      }
    },
    {
      "id": "heavy_duty_dolly_1",
      "name": "Heavy-Duty Dolly",
      "type": "FURNITURE",
      "location_id": "in:high_security_vault",
      "properties": {
        "size": [
          1.2,
          0.6,
          0.2
        ],
        "weight": 20.0,
        "is_container": false,
        "material": "metal",
        "color": "red"
      },
      "states": {
        "is_broken": true
      }
    },
    {
      "id": "authorized_personnel_sign_1",
      "name": "Peeling 'Authorized Personnel Only' Sign",
      "type": "FURNITURE",
      "location_id": "in:high_security_vault",
      "properties": {
        "size": [
          0.4,
          0.01,
          0.3
        ],
        "weight": 0.5,
        "is_container": false,
        "material": "plastic",
        "color": "red"
      },
      "states": {
        "is_ripped": false
      }
    },
    {
      "id": "constitution_frame_1",
      "name": "Dusty Framed Copy of the U.S. Constitution",
      "type": "FURNITURE",
      "location_id": "in:high_security_vault",
      "properties": {
        "size": [
          0.5,
          0.1,
          0.6
        ],
        "weight": 3.0,
        "is_container": false,
        "material": "wood",
        "color": "brown"
      },
      "states": {
        "is_dirty": true
      }
    },
    {
      "id": "light_table_1",
      "name": "Large Light Table",
      "type": "FURNITURE",
      "location_id": "in:document_restoration_lab",
      "properties": {
        "size": [
          1.8,
          1.2,
          0.8
        ],
        "weight": 60.0,
        "is_container": true,
        "material": "glass",
        "color": "white"
      },
      "states": {
        "is_broken": true
      }
    },
    {
      "id": "dehumidifier_1",
      "name": "Dehumidifier",
      "type": "FURNITURE",
      "location_id": "in:document_restoration_lab",
      "properties": {
        "size": [
          0.5,
          0.4,
          0.7
        ],
        "weight": 15.0,
        "is_container": false,
        "material": "plastic",
        "color": "white",
        "brand": "Frigidaire"
      },
      "states": {
        "is_dirty": true
      }
    },
    {
      "id": "water_damaged_file_8813_1",
      "name": "Water-Damaged Case File #8813",
      "type": "ITEM",
      "location_id": "on:light_table_1",
      "properties": {
        "weight": 0.8,
        "color": "yellowed",
        "material": "paper"
      },
      "states": {
        "is_wet": true
      }
    },
    {
      "id": "archival_glue_dispenser_1",
      "name": "Archival Glue Dispenser",
      "type": "ITEM",
      "location_id": "in:document_restoration_lab",
      "properties": {
        "weight": 0.5,
        "color": "white",
        "material": "plastic",
        "brand": "Lineco",
        "provides_abilities": [
          "glue"
        ]
      },
      "states": {
        "is_dirty": true
      }
    },
    {
      "id": "microfiber_cloth_1",
      "name": "Microfiber Cloth",
      "type": "ITEM",
      "location_id": "in:document_restoration_lab",
      "properties": {
        "weight": 0.1,
        "color": "blue",
        "material": "microfiber",
        "provides_abilities": [
          "clean",
          "dust",
          "dry"
        ]
      },
      "states": {
        "is_dirty": true
      }
    },
    {
      "id": "magnifying_glass_1",
      "name": "Magnifying Glass",
      "type": "ITEM",
      "location_id": "in:document_restoration_lab",
      "properties": {
        "weight": 0.3,
        "color": "black",
        "material": "glass",
        "brand": "Fresnel"
      },
      "states": {
        "is_dirty": true
      }
    },
    {
      "id": "law_journals_stack_1",
      "name": "Leaning Tower of Outdated Law Journals",
      "type": "ITEM",
      "location_id": "in:document_restoration_lab",
      "properties": {
        "weight": 10.0,
        "color": "various",
        "material": "paper",
        "quantity": 15
      },
      "states": {
        "is_assembled": false
      }
    },
    {
      "id": "motivational_poster_1",
      "name": "Faded Motivational Poster",
      "type": "FURNITURE",
      "location_id": "in:document_restoration_lab",
      "properties": {
        "size": [
          0.6,
          0.1,
          0.9
        ],
        "weight": 1.0,
        "is_container": false,
        "material": "paper",
        "color": "faded"
      },
      "states": {
        "is_dirty": true
      }
    },
    {
      "id": "metal_shelves_1",
      "name": "Floor-to-Ceiling Metal Shelves",
      "type": "FURNITURE",
      "location_id": "in:storage_catacombs",
      "properties": {
        "size": [
          2.0,
          0.8,
          3.0
        ],
        "weight": 200.0,
        "is_container": true,
        "material": "steel",
        "color": "gray"
      },
      "states": {
        "is_broken": true,
        "is_open": false
      }
    },
    {
      "id": "rolling_ladder_1",
      "name": "Rickety Rolling Ladder",
      "type": "FURNITURE",
      "location_id": "in:storage_catacombs",
      "properties": {
        "size": [
          1.8,
          0.5,
          3.0
        ],
        "weight": 50.0,
        "is_container": false,
        "material": "wood",
        "color": "brown"
      },
      "states": {
        "is_broken": true
      }
    },
    {
      "id": "misfiled_case_box_309_1",
      "name": "Misfiled Case Box #309",
      "type": "ITEM",
      "location_id": "in:metal_shelves_1",
      "properties": {
        "weight": 5.0,
        "color": "cardboard",
        "material": "paper",
        "label": "1985 (should be 1995)"
      },
      "states": {
        "is_hidden": false
      }
    },
    {
      "id": "overloaded_shelf_bracket_1",
      "name": "Overloaded Shelf Bracket",
      "type": "FURNITURE",
      "location_id": "in:storage_catacombs",
      "properties": {
        "size": [
          0.2,
          0.2,
          0.1
        ],
        "weight": 1.0,
        "is_container": false,
        "material": "metal",
        "color": "silver"
      },
      "states": {
        "is_broken": true
      }
    },
    {
      "id": "barcode_scanner_1",
      "name": "Barcode Scanner",
      "type": "ITEM",
      "location_id": "in:storage_catacombs",
      "properties": {
        "weight": 0.4,
        "color": "black",
        "material": "plastic",
        "brand": "Zebra"
      },
      "states": {
        "is_broken": true
      }
    },
    {
      "id": "vacuum_cleaner_1",
      "name": "Dusty Vacuum Cleaner",
      "type": "FURNITURE",
      "location_id": "in:storage_catacombs",
      "properties": {
        "size": [
          0.5,
          0.3,
          1.0
        ],
        "weight": 8.0,
        "is_container": false,
        "material": "plastic",
        "color": "yellow",
        "brand": "Hoover"
      },
      "states": {
        "is_dirty": true
      }
    },
    {
      "id": "cobwebs_1",
      "name": "Cobwebs in High Corners",
      "type": "ITEM",
      "location_id": "in:storage_catacombs",
      "properties": {
        "weight": 0.01,
        "color": "gray",
        "material": "silk"
      },
      "states": {
        "is_dirty": true
      }
    },
    {
      "id": "lunchbox_1",
      "name": "Forgotten Lunchbox",
      "type": "ITEM",
      "location_id": "in:storage_catacombs",
      "properties": {
        "weight": 1.0,
        "color": "rusted",
        "material": "metal",
        "brand": "Thermos"
      },
      "states": {
        "is_frozen": true
      }
    },
    {
      "id": "sealed_evidence_crate_1",
      "name": "Sealed Evidence Crate",
      "type": "FURNITURE",
      "location_id": "in:storage_catacombs",
      "properties": {
        "size": [
          1.2,
          0.8,
          0.8
        ],
        "weight": 60.0,
        "is_container": true,
        "material": "wood",
        "color": "brown"
      },
      "states": {
        "is_open": false
      }
    },
    {
      "id": "collapsing_shelf_1",
      "name": "Collapsing Shelf",
      "type": "FURNITURE",
      "location_id": "in:storage_catacombs",
      "properties": {
        "size": [
          2.0,
          0.8,
          3.0
        ],
        "weight": 150.0,
        "is_container": true,
        "material": "steel",
        "color": "gray"
      },
      "states": {
        "is_broken": true
      }
    },
    {
      "id": "repair_kit_1",
      "name": "Document Repair Kit",
      "type": "ITEM",
      "location_id": "in:document_restoration_lab",
      "properties": {
        "weight": 2.0,
        "color": "blue",
        "material": "plastic",
        "brand": "Archival Methods",
        "provides_abilities": [
          "repair",
          "glue",
          "clean"
        ]
      },
      "states": {}
    },
    {
      "id": "screwdriver_1",
      "name": "Phillips Screwdriver",
      "type": "ITEM",
      "location_id": "in:document_restoration_lab",
      "properties": {
        "weight": 0.3,
        "color": "yellow",
        "material": "metal",
        "brand": "Craftsman",
        "provides_abilities": [
          "screw"
        ]
      },
      "states": {}
    },
    {
      "id": "sandpaper_1",
      "name": "Fine-Grit Sandpaper",
      "type": "ITEM",
      "location_id": "in:document_restoration_lab",
      "properties": {
        "weight": 0.1,
        "color": "tan",
        "material": "abrasive",
        "grit": 220,
        "provides_abilities": [
          "sand"
        ]
      },
      "states": {}
    },
    {
      "id": "paperclip_1",
      "name": "Paperclip",
      "type": "ITEM",
      "location_id": "in:document_restoration_lab",
      "properties": {
        "weight": 0.01,
        "color": "silver",
        "material": "metal",
        "provides_abilities": [
          "rip"
        ]
      },
      "states": {}
    },
    {
      "id": "backup_key_1",
      "name": "Backup Key",
      "type": "ITEM",
      "location_id": "in:fireproof_safe_1",
      "properties": {
        "weight": 0.05,
        "color": "brass",
        "material": "metal",
        "provides_abilities": [
          "open"
        ]
      },
      "states": {}
    }
  ],
  "abilities": [
    "clean",
    "dry",
    "dust",
    "format",
    "glue",
    "hide",
    "open",
    "repair",
    "rip",
    "sand",
    "screw",
    "thaw",
    "close"
  ]
}