{
  "description": "A bustling tech repair and development workshop with multiple workstations, heavy equipment, and precision tools for collaborative device repair and prototyping.",
  "rooms": [
    {
      "id": "diagnostic_testing_bay",
      "name": "Diagnostic & Testing Bay",
      "properties": {
        "type": "workshop"
      },
      "connected_to_room_ids": [
        "component_storage",
        "software_dev_corner",
        "repair_station"
      ]
    },
    {
      "id": "component_storage",
      "name": "Component Storage & Inventory",
      "properties": {
        "type": "storage"
      },
      "connected_to_room_ids": [
        "diagnostic_testing_bay",
        "software_dev_corner"
      ]
    },
    {
      "id": "software_dev_corner",
      "name": "Software Development Corner",
      "properties": {
        "type": "workspace"
      },
      "connected_to_room_ids": [
        "diagnostic_testing_bay",
        "component_storage"
      ]
    },
    {
      "id": "repair_station",
      "name": "Breakdown & Repair Station",
      "properties": {
        "type": "workshop"
      },
      "connected_to_room_ids": [
        "diagnostic_testing_bay"
      ]
    }
  ],
  "objects": [
    {
      "id": "central_workbench_1",
      "name": "Central Workbench",
      "type": "FURNITURE",
      "location_id": "in:diagnostic_testing_bay",
      "properties": {
        "size": [
          2.0,
          1.5,
          0.9
        ],
        "weight": 85.0,
        "is_container": true,
        "material": "steel",
        "surface": "ESD-safe"
      },
      "states": {}
    },
    {
      "id": "multi_device_test_rig_1",
      "name": "Multi-Device Test Rig",
      "type": "FURNITURE",
      "location_id": "on:central_workbench_1",
      "properties": {
        "size": [
          0.6,
          0.4,
          0.3
        ],
        "weight": 25.0,
        "is_container": false,
        "capacity": "6 phones",
        "model": "Diagnostic Pro 3000"
      },
      "states": {
        "is_on": false
      }
    },
    {
      "id": "overhead_magnifying_lamp_1",
      "name": "Overhead Magnifying Lamp",
      "type": "FURNITURE",
      "location_id": "in:diagnostic_testing_bay",
      "properties": {
        "size": [
          0.5,
          0.5,
          1.2
        ],
        "weight": 12.0,
        "is_container": false,
        "led_color": "flickering",
        "adjustable": true
      },
      "states": {
        "is_on": false
      }
    },
    {
      "id": "bricked_iphone_4_1",
      "name": "Bricked iPhone 4",
      "type": "ITEM",
      "location_id": "on:central_workbench_1",
      "properties": {
        "weight": 0.14,
        "color": "black",
        "serial_number": "A1342B",
        "issue": "power button stuck, boot loop"
      },
      "states": {
        "is_mounted": false,
        "is_mended": false
      }
    },
    {
      "id": "flashing_jig_1",
      "name": "Flashing Jig",
      "type": "ITEM",
      "location_id": "on:central_workbench_1",
      "properties": {
        "weight": 0.5,
        "connection": "USB",
        "label": "FOR iOS 9.3.5 ONLY",
        "provides_abilities": [
          "start_engine"
        ]
      },
      "states": {}
    },
    {
      "id": "rf_shielded_test_chamber_1",
      "name": "RF Shielded Test Chamber",
      "type": "FURNITURE",
      "location_id": "in:diagnostic_testing_bay",
      "properties": {
        "size": [
          0.8,
          0.6,
          0.8
        ],
        "weight": 75.0,
        "is_container": true,
        "condition": "door slightly bent"
      },
      "states": {
        "is_open": false
      }
    },
    {
      "id": "digital_multimeter_1",
      "name": "Digital Multimeter",
      "type": "ITEM",
      "location_id": "on:central_workbench_1",
      "properties": {
        "weight": 0.3,
        "battery_status": "low",
        "probe_condition": "worn tips",
        "provides_abilities": [
          "disarm_alarm"
        ]
      },
      "states": {}
    },
    {
      "id": "wireless_charging_pad_1",
      "name": "Wireless Charging Pad",
      "type": "ITEM",
      "location_id": "on:central_workbench_1",
      "properties": {
        "weight": 0.2,
        "compatibility": "Qi",
        "surface_condition": "tape residue"
      },
      "states": {
        "is_on": false
      }
    },
    {
      "id": "repair_log_clipboard_1",
      "name": "Repair Log Clipboard",
      "type": "ITEM",
      "location_id": "on:central_workbench_1",
      "properties": {
        "weight": 0.4,
        "status": "half-filled",
        "condition": "coffee-stained"
      },
      "states": {
        "is_covered": true
      }
    },
    {
      "id": "industrial_shelving_unit_1",
      "name": "Industrial Shelving Unit",
      "type": "FURNITURE",
      "location_id": "in:component_storage",
      "properties": {
        "size": [
          1.8,
          0.6,
          2.0
        ],
        "weight": 90.0,
        "is_container": true,
        "condition": "slightly wobbly left leg"
      },
      "states": {}
    },
    {
      "id": "locked_component_cabinet_1",
      "name": "Locked Component Cabinet",
      "type": "FURNITURE",
      "location_id": "in:component_storage",
      "properties": {
        "size": [
          1.2,
          0.6,
          1.8
        ],
        "weight": 65.0,
        "is_container": true,
        "lock_type": "digital keypad",
        "last_code": "1984"
      },
      "states": {
        "is_open": false
      }
    },
    {
      "id": "iphone_3g_logic_board_1",
      "name": "iPhone 3G Logic Board",
      "type": "ITEM",
      "location_id": "on:industrial_shelving_unit_1",
      "properties": {
        "weight": 0.1,
        "condition": "corroded contacts",
        "tag": "FOR SALVAGE"
      },
      "states": {
        "is_mounted": false,
        "is_mended": false
      }
    },
    {
      "id": "battery_bin_1",
      "name": "Battery Bin",
      "type": "FURNITURE",
      "location_id": "on:industrial_shelving_unit_1",
      "properties": {
        "size": [
          0.4,
          0.3,
          0.2
        ],
        "weight": 55.0,
        "is_container": true,
        "hazard": "DO NOT CRUSH",
        "contents": "mixed Li-ion cells, some swollen"
      },
      "states": {
        "is_open": false
      }
    },
    {
      "id": "micro_screw_organizer_1",
      "name": "Micro-Screw Organizer",
      "type": "ITEM",
      "location_id": "on:industrial_shelving_unit_1",
      "properties": {
        "weight": 1.2,
        "compartments": 64,
        "missing_screws": "Pentalobe 1.2mm",
        "provides_abilities": [
          "mount"
        ]
      },
      "states": {}
    },
    {
      "id": "barcode_scanner_1",
      "name": "Barcode Scanner",
      "type": "ITEM",
      "location_id": "on:industrial_shelving_unit_1",
      "properties": {
        "weight": 0.4,
        "condition": "battery cover missing",
        "last_used": "2 days ago"
      },
      "states": {
        "is_on": false
      }
    },
    {
      "id": "label_maker_1",
      "name": "Label Maker",
      "type": "ITEM",
      "location_id": "on:industrial_shelving_unit_1",
      "properties": {
        "weight": 0.8,
        "status": "out of tape",
        "note": "REPLACE SOON"
      },
      "states": {
        "is_open": false
      }
    },
    {
      "id": "esd_safe_stool_1",
      "name": "ESD-Safe Stool",
      "type": "FURNITURE",
      "location_id": "in:component_storage",
      "properties": {
        "size": [
          0.4,
          0.4,
          0.5
        ],
        "weight": 15.0,
        "condition": "wheels squeaky, height adjustment stiff"
      },
      "states": {}
    },
    {
      "id": "dev_monitor_1",
      "name": "Development Monitor",
      "type": "FURNITURE",
      "location_id": "in:software_dev_corner",
      "properties": {
        "size": [
          0.6,
          0.1,
          0.4
        ],
        "weight": 12.0,
        "is_container": true,
        "brand": "Dell",
        "model": "UltraSharp 27"
      },
      "states": {
        "is_on": false
      }
    },
    {
      "id": "dev_keyboard_1",
      "name": "Development Keyboard",
      "type": "ITEM",
      "location_id": "on:dev_monitor_1",
      "properties": {
        "weight": 0.9,
        "type": "mechanical",
        "switch_type": "Cherry MX Brown",
        "is_container": true
      },
      "states": {
        "is_covered": true,
        "is_open": false
      }
    },
    {
      "id": "firmware_usb_1",
      "name": "Firmware USB Drive",
      "type": "ITEM",
      "location_id": "in:dev_keyboard_1",
      "properties": {
        "weight": 0.05,
        "capacity": "32GB",
        "contents": "firmware files",
        "provides_abilities": [
          "start_engine"
        ]
      },
      "states": {
        "is_hidden": true
      }
    },
    {
      "id": "repair_microscope_1",
      "name": "Repair Microscope",
      "type": "FURNITURE",
      "location_id": "in:repair_station",
      "properties": {
        "size": [
          0.4,
          0.3,
          0.5
        ],
        "weight": 18.0,
        "magnification": "10x-40x",
        "light_type": "LED ring"
      },
      "states": {
        "is_on": false
      }
    },
    {
      "id": "soldering_iron_1",
      "name": "Soldering Iron",
      "type": "ITEM",
      "location_id": "in:repair_station",
      "properties": {
        "weight": 0.6,
        "temperature_range": "200-450°C",
        "tip_condition": "slightly oxidized",
        "provides_abilities": [
          "mend"
        ]
      },
      "states": {}
    },
    {
      "id": "anti_static_mat_1",
      "name": "Anti-Static Mat",
      "type": "FURNITURE",
      "location_id": "in:repair_station",
      "properties": {
        "size": [
          1.0,
          0.8,
          0.01
        ],
        "weight": 3.0,
        "material": "rubber",
        "condition": "slightly worn edges",
        "is_container": true
      },
      "states": {}
    },
    {
      "id": "precision_screwdriver_set_1",
      "name": "Precision Screwdriver Set",
      "type": "ITEM",
      "location_id": "on:anti_static_mat_1",
      "properties": {
        "weight": 0.3,
        "bits_included": 24,
        "missing_bits": "Pentalobe 1.2mm",
        "provides_abilities": [
          "mount"
        ]
      },
      "states": {}
    },
    {
      "id": "blue_screwdriver_1",
      "name": "Blue Screwdriver",
      "type": "ITEM",
      "location_id": "on:anti_static_mat_1",
      "properties": {
        "weight": 0.1,
        "warning": "DON'T USE - STRIPS HEADS",
        "condition": "worn tip"
      },
      "states": {}
    },
    {
      "id": "tweezers_1",
      "name": "Anti-Static Tweezers",
      "type": "ITEM",
      "location_id": "on:anti_static_mat_1",
      "properties": {
        "weight": 0.05,
        "tip_type": "angled",
        "material": "ESD-safe"
      },
      "states": {}
    },
    {
      "id": "cleaning_cloth_1",
      "name": "Microfiber Cleaning Cloth",
      "type": "ITEM",
      "location_id": "on:anti_static_mat_1",
      "properties": {
        "weight": 0.1,
        "material": "microfiber",
        "condition": "slightly dirty",
        "provides_abilities": [
          "dry"
        ]
      },
      "states": {}
    },
    {
      "id": "swollen_battery_1",
      "name": "Swollen iPhone Battery",
      "type": "ITEM",
      "location_id": "in:battery_bin_1",
      "properties": {
        "weight": 0.08,
        "condition": "swollen",
        "voltage": "0.0V",
        "hazard": "high"
      },
      "states": {}
    },
    {
      "id": "good_battery_1",
      "name": "Good iPhone Battery",
      "type": "ITEM",
      "location_id": "in:battery_bin_1",
      "properties": {
        "weight": 0.07,
        "condition": "good",
        "voltage": "3.82V",
        "led_color": "green"
      },
      "states": {}
    },
    {
      "id": "locked_drawer_1",
      "name": "Locked Tool Drawer",
      "type": "FURNITURE",
      "location_id": "in:repair_station",
      "properties": {
        "size": [
          0.5,
          0.4,
          0.2
        ],
        "weight": 12.0,
        "is_container": true,
        "lock_type": "key"
      },
      "states": {
        "is_open": false
      }
    },
    {
      "id": "drawer_key_1",
      "name": "Drawer Key",
      "type": "ITEM",
      "location_id": "on:dev_keyboard_1",
      "properties": {
        "weight": 0.02,
        "material": "brass",
        "fits": "locked_drawer_1"
      },
      "states": {
        "is_hidden": true
      }
    },
    {
      "id": "soldering_tip_cleaner_1",
      "name": "Soldering Tip Cleaner",
      "type": "ITEM",
      "location_id": "in:locked_drawer_1",
      "properties": {
        "weight": 0.2,
        "material": "brass wool",
        "provides_abilities": [
          "sharpen"
        ]
      },
      "states": {}
    },
    {
      "id": "spare_solder_roll_1",
      "name": "Spare Solder Roll",
      "type": "ITEM",
      "location_id": "in:locked_drawer_1",
      "properties": {
        "weight": 0.15,
        "alloy": "60/40",
        "diameter": "0.5mm"
      },
      "states": {
        "is_covered": true
      }
    },
    {
      "id": "flux_pen_1",
      "name": "Flux Pen",
      "type": "ITEM",
      "location_id": "in:locked_drawer_1",
      "properties": {
        "weight": 0.05,
        "remaining": "30%",
        "type": "rosin"
      },
      "states": {}
    },
    {
      "id": "help_manual_1",
      "name": "iPhone Repair Manual",
      "type": "ITEM",
      "location_id": "on:central_workbench_1",
      "properties": {
        "weight": 0.7,
        "edition": "2022",
        "condition": "dog-eared pages"
      },
      "states": {
        "is_open": false
      }
    },
    {
      "id": "think_different_poster_1",
      "name": "Vintage Think Different Poster",
      "type": "FURNITURE",
      "location_id": "in:diagnostic_testing_bay",
      "properties": {
        "size": [
          0.8,
          0.6,
          0.02
        ],
        "weight": 2.0,
        "condition": "slightly crooked, edges yellowed"
      },
      "states": {}
    },
    {
      "id": "tech_magazines_1",
      "name": "Stack of Tech Magazines",
      "type": "ITEM",
      "location_id": "on:central_workbench_1",
      "properties": {
        "weight": 1.5,
        "titles": "Wired, 2017",
        "condition": "outdated"
      },
      "states": {}
    },
    {
      "id": "warning_note_1",
      "name": "Warning Sticky Note",
      "type": "ITEM",
      "location_id": "on:dev_monitor_1",
      "properties": {
        "weight": 0.01,
        "message": "DON'T USE BLUE SCREWDRIVER—STRIPS HEADS!",
        "color": "yellow"
      },
      "states": {}
    },
    {
      "id": "employee_plaque_1",
      "name": "Employee of the Month Plaque",
      "type": "FURNITURE",
      "location_id": "in:component_storage",
      "properties": {
        "size": [
          0.3,
          0.2,
          0.05
        ],
        "weight": 1.2,
        "condition": "dusty, name scratched off"
      },
      "states": {}
    },
    {
      "id": "old_chips_1",
      "name": "Half-Eaten Bag of Chips",
      "type": "ITEM",
      "location_id": "on:industrial_shelving_unit_1",
      "properties": {
        "weight": 0.2,
        "flavor": "sour cream",
        "status": "expired"
      },
      "states": {}
    },
    {
      "id": "graffiti_1",
      "name": "Wall Graffiti",
      "type": "FURNITURE",
      "location_id": "in:component_storage",
      "properties": {
        "size": [
          1.0,
          0.5,
          0.01
        ],
        "weight": 0.1,
        "message": "THEY SAID IT COULDN'T BE JAILBREAKED",
        "color": "black spray paint"
      },
      "states": {}
    }
  ],
  "abilities": [
    "disarm_alarm",
    "dry",
    "mend",
    "mount",
    "open",
    "sharpen",
    "show",
    "start_engine",
    "turn_on",
    "uncover",
    "close"
  ]
}