{
  "task_background": "Prepare the Algal Research and Emergency Response Laboratory for immediate nitrogen-depletion crisis mitigation.",
  "agents_config": [
    {
      "name": "robot_1",
      "max_grasp_limit": 30.0,
      "max_weight": 50.0,
      "max_size": 100.0
    }
  ],
  "tasks": [
    {
      "task_description": "Use the fuel canister to refuel the emergency nitrogen injection port.",
      "task_category": "compound_reasoning",
      "validation_checks": [
        {
          "id": "emergency_nitrogen_port_1",
          "is_fueled": true
        }
      ]
    }
  ],
  "scene_id": "00485"
}