{
  "task_background": "Prepare the Network Operations Center (NOC) for an upcoming network maintenance session.",
  "agents_config": [
    {
      "name": "robot_1",
      "max_grasp_limit": 1,
      "max_weight": 25.0,
      "max_size": [
        1.0,
        1.0,
        1.0
      ]
    }
  ],
  "tasks": [
    {
      "task_description": "Use the thermal_camera_1 to scan the server_rack_7 and then turn on the hvac_panel_1.",
      "task_category": "compound_reasoning",
      "validation_checks": [
        {
          "id": "server_rack_7",
          "is_scanned": true
        },
        {
          "id": "hvac_panel_1",
          "is_scanned": true
        }
      ]
    }
  ],
  "scene_id": "00849"
}