{
  "task_background": "Prepare the digital media production studio for the upcoming YouTube revenue-sharing program launch.",
  "agents_config": [
    {
      "name": "robot_1",
      "max_grasp_limit": 1,
      "max_weight": 25.0,
      "max_size": [
        1.5,
        1.5,
        1.8
      ]
    },
    {
      "name": "robot_2",
      "max_grasp_limit": 1,
      "max_weight": 25.0,
      "max_size": [
        1.5,
        1.5,
        1.8
      ]
    }
  ],
  "tasks": [
    {
      "task_description": "Move the lighting_rig_1 to the equipment_storage.",
      "task_category": "implicit_collaboration",
      "validation_checks": [
        {
          "id": "lighting_rig_1",
          "location_id": "in:equipment_storage"
        }
      ]
    }
  ],
  "scene_id": "00281"
}