{
  "task_background": "Prepare the Osbourne Family's Rockstar-Chaos Home Studio for an upcoming recording session by organizing, cleaning, and repairing equipment.",
  "agents_config": [
    {
      "name": "robot_1",
      "max_grasp_limit": 1.0,
      "max_weight": 30.0,
      "max_size": [
        1.0,
        1.0,
        1.0
      ]
    }
  ],
  "tasks": [
    {
      "task_description": "Find the heaviest, metal object in the main_recording_studio and place it in the hallway_storage_closet.",
      "task_category": "attribute_reasoning",
      "validation_checks": [
        {
          "id": "mixing_console_1",
          "location_id": "in:hallway_storage_closet"
        }
      ]
    }
  ],
  "scene_id": "00542"
}