{
  "task_background": "Reset the loft apartment for a new day of gaming and fitness activities.",
  "agents_config": [
    {
      "name": "robot_1",
      "max_grasp_limit": 3,
      "max_weight": 50.0,
      "max_size": [
        100.0,
        100.0,
        100.0
      ]
    },
    {
      "name": "robot_2",
      "max_grasp_limit": 3,
      "max_weight": 50.0,
      "max_size": [
        100.0,
        100.0,
        100.0
      ]
    }
  ],
  "tasks": [
    {
      "task_description": "Place shared_monitor_1 on gaming_desk_2.",
      "task_category": "direct_command",
      "validation_checks": [
        {
          "id": "shared_monitor_1",
          "location_id": "on:gaming_desk_2"
        }
      ]
    },
    {
      "task_description": "Move accountability_jar_1 to kitchenette.",
      "task_category": "direct_command",
      "validation_checks": [
        {
          "id": "accountability_jar_1",
          "location_id": ":kitchenette"
        }
      ]
    },
    {
      "task_description": "Bring the frayed resistance band to the gaming corner.",
      "task_category": "attribute_reasoning",
      "validation_checks": [
        {
          "id": "resistance_band_red_1",
          "location_id": ":gaming_corner"
        }
      ]
    },
    {
      "task_description": "Place the deflated medicine ball on the sectional couch.",
      "task_category": "attribute_reasoning",
      "validation_checks": [
        {
          "id": "medicine_ball_1",
          "location_id": "on:sectional_couch_1"
        }
      ]
    },
    {
      "task_description": "Use the wrench to tighten the only dumbbell in the gym zone with a stuck dial.",
      "task_category": "compound_reasoning",
      "validation_checks": [
        {
          "id": "loose_screw_dumbbell_1",
          "is_loose": false
        }
      ]
    },
    {
      "task_description": "Mend the torn shirt in the living room using the sewing kit.",
      "task_category": "compound_reasoning",
      "validation_checks": [
        {
          "id": "torn_workout_shirt_1",
          "is_mended": true
        }
      ]
    },
    {
      "task_description": "Have robot_1 and robot_2 cooperate to lower the sectional couch.",
      "task_category": "explicit_collaboration",
      "validation_checks": [
        {
          "id": "sectional_couch_1",
          "is_lowered": true
        }
      ]
    },
    {
      "task_description": "Have robot_1 and robot_2 cooperate to open the mini fridge.",
      "task_category": "explicit_collaboration",
      "validation_checks": [
        {
          "id": "mini_fridge_1",
          "is_open": true
        }
      ]
    },
    {
      "task_description": "Move the foldable treadmill to the makeshift gym zone.",
      "task_category": "implicit_collaboration",
      "validation_checks": [
        {
          "id": "foldable_treadmill_1",
          "location_id": ":makeshift_gym_zone"
        }
      ]
    },
    {
      "task_description": "Relocate the sectional couch to the gaming corner.",
      "task_category": "implicit_collaboration",
      "validation_checks": [
        {
          "id": "sectional_couch_1",
          "location_id": ":gaming_corner"
        }
      ]
    },
    {
      "task_description": "Cooperatively move the foldable treadmill displaying error E3 to the kitchenette.",
      "task_category": "compound_collaboration",
      "validation_checks": [
        {
          "id": "foldable_treadmill_1",
          "location_id": ":kitchenette"
        }
      ]
    },
    {
      "task_description": "Cooperatively move the sectional couch that is not lowered to the gym zone.",
      "task_category": "compound_collaboration",
      "validation_checks": [
        {
          "id": "sectional_couch_1",
          "location_id": ":makeshift_gym_zone"
        }
      ]
    }
  ],
  "scene_id": "01085"
}